folderspy/__init__.py
folderspy/__version__.py
folderspy/spy.py
folderspy/linux/__init__.py
folderspy/linux/folder.py
folderspy/linux/spy.py
folderspy/mac/__init__.py
folderspy/mac/folder.py
folderspy/mac/spy.py
folderspy/windows/__init__.py
folderspy/windows/folder.py
folderspy/windows/spy.py
folderspy/windows/watcher.py
folderspy-0.0.5.dist-info/LICENSE
folderspy-0.0.5.dist-info/METADATA
folderspy-0.0.5.dist-info/WHEEL
folderspy-0.0.5.dist-info/top_level.txt
folderspy-0.0.5.dist-info/RECORD
