Metadata-Version: 2.1
Name: folderspy
Version: 0.0.5
Summary: Watch folders for file/directory events with a simple API.
Home-page: https://github.com/rob-white/folderspy
Author: Rob White
Author-email: robathan4@gmail.com
License: UNKNOWN
Platform: UNKNOWN
Classifier: License :: OSI Approved :: MIT License
Classifier: Programming Language :: Python :: 2
Classifier: Programming Language :: Python :: 2.7
Classifier: Programming Language :: Python :: 3
Classifier: Programming Language :: Python :: 3.4
Classifier: Programming Language :: Python :: 3.5
Classifier: Programming Language :: Python :: 3.6
Classifier: Programming Language :: Python :: 3.7
Requires-Dist: MacFSEvents; platform_system == "Darwin"
Requires-Dist: pyinotify; platform_system == "Linux"
Requires-Dist: pypiwin32; platform_system == "Windows"
